{
  "title": "Parsippany -Troy Hills STEM Pathways",
  "outline": [
    {
      "level": "H3",
      "text": "Mission Statement:",
      "page": 1
    },
    {
      "level": "H3",
      "text": "Goals:",
      "page": 1
    },
    {
      "level": "H4",
      "text": "PATHWAY OPTIONS",
      "page": 1
    },
    {
      "level": "H4",
      "text": "REGULAR PATHWAY DISTINCTION PATHWAY",
      "page": 1
    },
    {
      "level": "H3",
      "text": "Elective Course Offerings",
      "page": 2
    },
    {
      "level": "H3",
      "text": "Science Math Computer Science/ Art Applied",
      "page": 2
    },
    {
      "level": "H3",
      "text": "What Colleges Say!",
      "page": 2
    },
    {
      "level": "H3",
      "text": "“Would participation in the Drew University:",
      "page": 2
    },
    {
      "level": "H3",
      "text": "For more information and our application please visit our website by clicking here",
      "page": 2
    }
  ]
}